thangdemo/__init__.py
thangdemo/core.py
thangdemo-0.1.0.dist-info/licenses/LICENSE
thangdemo-0.1.0.dist-info/METADATA
thangdemo-0.1.0.dist-info/WHEEL
thangdemo-0.1.0.dist-info/entry_points.txt
thangdemo-0.1.0.dist-info/top_level.txt
thangdemo-0.1.0.dist-info/RECORD
